kiwi/__init__.py
kiwi/__installed__.py
kiwi/__version__.py
kiwi/accessor.py
kiwi/argcheck.py
kiwi/component.py
kiwi/controllers.py
kiwi/currency.py
kiwi/datatypes.py
kiwi/decorators.py
kiwi/desktopparser.py
kiwi/dist.py
kiwi/enums.py
kiwi/environ.py
kiwi/interfaces.py
kiwi/log.py
kiwi/model.py
kiwi/python.py
kiwi/tasklet.py
kiwi/utils.py
kiwi/i18n/__init__.py
kiwi/i18n/i18n.py
kiwi/i18n/msgfmt.py
kiwi/ui/__init__.py
kiwi/ui/builderloader.py
kiwi/ui/cellrenderer.py
kiwi/ui/comboentry.py
kiwi/ui/dateentry.py
kiwi/ui/delegates.py
kiwi/ui/dialogs.py
kiwi/ui/entry.py
kiwi/ui/entrycompletion.py
kiwi/ui/forms.py
kiwi/ui/gadgets.py
kiwi/ui/gaxmlloader.py
kiwi/ui/hyperlink.py
kiwi/ui/libgladeloader.py
kiwi/ui/listdialog.py
kiwi/ui/multicombo.py
kiwi/ui/objectlist.py
kiwi/ui/pixbufutils.py
kiwi/ui/popup.py
kiwi/ui/proxy.py
kiwi/ui/proxywidget.py
kiwi/ui/signal.py
kiwi/ui/tooltip.py
kiwi/ui/views.py
kiwi/ui/test/__init__.py
kiwi/ui/test/common.py
kiwi/ui/test/main.py
kiwi/ui/test/recorder.py
kiwi/ui/test/runner.py
kiwi/ui/widgets/__init__.py
kiwi/ui/widgets/button.py
kiwi/ui/widgets/checkbutton.py
kiwi/ui/widgets/colorbutton.py
kiwi/ui/widgets/combo.py
kiwi/ui/widgets/contextmenu.py
kiwi/ui/widgets/entry.py
kiwi/ui/widgets/filechooser.py
kiwi/ui/widgets/fontbutton.py
kiwi/ui/widgets/label.py
kiwi/ui/widgets/multicombo.py
kiwi/ui/widgets/radiobutton.py
kiwi/ui/widgets/scale.py
kiwi/ui/widgets/spinbutton.py
kiwi/ui/widgets/textview.py
kiwi_gtk-3.0.4.data/data/lib/glade3/modules/kiwiwidgets.py
kiwi_gtk-3.0.4.data/data/share/doc/kiwi/AUTHORS
kiwi_gtk-3.0.4.data/data/share/doc/kiwi/NEWS
kiwi_gtk-3.0.4.data/data/share/doc/kiwi/README
kiwi_gtk-3.0.4.data/data/share/glade3/catalogs/kiwiwidgets.xml
kiwi_gtk-3.0.4.data/data/share/glade3/pixmaps/hyperlink.png
kiwi_gtk-3.0.4.data/data/share/glade3/pixmaps/kiwibutton.png
kiwi_gtk-3.0.4.data/data/share/glade3/pixmaps/kiwicheckbutton.png
kiwi_gtk-3.0.4.data/data/share/glade3/pixmaps/kiwicolorbutton.png
kiwi_gtk-3.0.4.dist-info/AUTHORS
kiwi_gtk-3.0.4.dist-info/COPYING
kiwi_gtk-3.0.4.dist-info/METADATA
kiwi_gtk-3.0.4.dist-info/WHEEL
kiwi_gtk-3.0.4.dist-info/top_level.txt
kiwi_gtk-3.0.4.dist-info/RECORD
