Metadata-Version: 2.1
Name: kiwi-gtk
Version: 3.0.4
Summary: A framework and a set of enhanced widgets based on PyGTK
Home-page: https://github.com/stoq/kiwi
Author: Stoq Tecnologia
Author-email: dev@stoq.com.br
License: GNU LGPL 2.1 (see COPYING)
Platform: UNKNOWN
Requires-Dist: setuptools (>=0.8)
